rimseval/__init__.py
rimseval/compatibility/__init__.py
rimseval/compatibility/lion_eval.py
rimseval/data_io/__init__.py
rimseval/data_io/crd_reader.py
rimseval/data_io/crd_utils.py
rimseval/data_io/excel_writer.py
rimseval/data_io/export.py
rimseval/data_io/integrals.py
rimseval/data_io/kore_to_crd.py
rimseval/data_io/lst_to_crd.py
rimseval/data_io/lst_utils.py
rimseval/guis/__init__.py
rimseval/guis/integrals.py
rimseval/guis/mcal.py
rimseval/guis/mpl_canvas.py
rimseval/guis/plots.py
rimseval/interfacer.py
rimseval/multi_proc.py
rimseval/processor.py
rimseval/processor_utils.py
rimseval/utilities/__init__.py
rimseval/utilities/fitting.py
rimseval/utilities/peirce.py
rimseval/utilities/utils.py
rimseval-2.1.0.dist-info/WHEEL
rimseval-2.1.0.dist-info/METADATA
rimseval-2.1.0.dist-info/RECORD
