Metadata-Version: 2.3
Name: rimseval
Version: 2.1.0
Summary: Evaluate resonance ionization mass spectrometry measurements, correct, and filter. Contains a reader for crd files (Chicago Raw Data) but can also convert FastComTec lst files to crd.
Author: Reto Trappitsch
Author-email: Reto Trappitsch <reto@galactic-forensics.space>
License: MIT
Requires-Dist: iniabu>=1.1.2
Requires-Dist: matplotlib
Requires-Dist: numba~=0.61
Requires-Dist: numpy~=2.2
Requires-Dist: pyqt6
Requires-Dist: scipy
Requires-Dist: xlsxwriter
Requires-Python: >=3.10, <3.13
Project-URL: Documentation, https://rimseval.readthedocs.io
Project-URL: Source, https://github.com/RIMS-Code/RIMSEval
